textcomplexity/__init__.py
textcomplexity/cli.py
textcomplexity/compression.py
textcomplexity/constituency.py
textcomplexity/de.json
textcomplexity/dependency.py
textcomplexity/en.json
textcomplexity/pos.py
textcomplexity/sentence.py
textcomplexity/surface.py
textcomplexity/text.py
textcomplexity/version.py
textcomplexity/vocabulary_richness.py
textcomplexity/utils/__init__.py
textcomplexity/utils/conllu.py
textcomplexity/utils/custom_tsv.py
textcomplexity/utils/graph.py
textcomplexity/utils/misc.py
textcomplexity/utils/text.py
textcomplexity/utils/token.py
textcomplexity/utils/windows.py
textcomplexity-0.11.0.data/scripts/txtcomplexity
textcomplexity-0.11.0.dist-info/LICENSE.txt
textcomplexity-0.11.0.dist-info/METADATA
textcomplexity-0.11.0.dist-info/WHEEL
textcomplexity-0.11.0.dist-info/top_level.txt
textcomplexity-0.11.0.dist-info/RECORD
