Metadata-Version: 2.1
Name: textcomplexity
Version: 0.11.0
Summary: Linguistic and stylistic complexity measures for text
Home-page: https://github.com/tsproisl/textcomplexity
Download-URL: https://github.com/tsproisl/textcomplexity/archive/v0.11.0.tar.gz
Author: Thomas Proisl
Author-email: thomas.proisl@fau.de
License: GNU General Public License v3 or later (GPLv3+)
Platform: UNKNOWN
Classifier: Development Status :: 4 - Beta
Classifier: Environment :: Console
Classifier: Intended Audience :: Developers
Classifier: Intended Audience :: Science/Research
Classifier: License :: OSI Approved :: GNU General Public License v3 or later (GPLv3+)
Classifier: Operating System :: OS Independent
Classifier: Programming Language :: Python :: 3
Classifier: Topic :: Text Processing :: Linguistic
License-File: LICENSE.txt
Requires-Dist: networkx
Requires-Dist: nltk
Requires-Dist: nltk-tgrep
Requires-Dist: numpy
Requires-Dist: scipy
